ipydocs/__init__.py
ipydocs/__main__.py
ipydocs/components/__init__.py
ipydocs/parsing/__init__.py
ipydocs/parsing/classes.py
ipydocs/parsing/examples.py
ipydocs/parsing/functions.py
ipydocs-0.0.1.dist-info/METADATA
ipydocs-0.0.1.dist-info/WHEEL
ipydocs-0.0.1.dist-info/entry_points.txt
ipydocs-0.0.1.dist-info/RECORD
